aws_emr_launch/__init__.py
aws_emr_launch/constructs/__init__.py
aws_emr_launch/constructs/base.py
aws_emr_launch/constructs/emr_constructs/__init__.py
aws_emr_launch/constructs/emr_constructs/cluster_configuration.py
aws_emr_launch/constructs/emr_constructs/emr_code.py
aws_emr_launch/constructs/emr_constructs/emr_profile.py
aws_emr_launch/constructs/iam_roles/__init__.py
aws_emr_launch/constructs/iam_roles/emr_roles.py
aws_emr_launch/constructs/lambdas/__init__.py
aws_emr_launch/constructs/lambdas/emr_lambdas.py
aws_emr_launch/constructs/managed_configurations/__init__.py
aws_emr_launch/constructs/managed_configurations/autoscaling_configuration.py
aws_emr_launch/constructs/managed_configurations/instance_fleet_configuration.py
aws_emr_launch/constructs/managed_configurations/instance_group_configuration.py
aws_emr_launch/constructs/security_groups/__init__.py
aws_emr_launch/constructs/security_groups/emr.py
aws_emr_launch/constructs/step_functions/__init__.py
aws_emr_launch/constructs/step_functions/emr_chains.py
aws_emr_launch/constructs/step_functions/emr_launch_function.py
aws_emr_launch/constructs/step_functions/emr_tasks.py
aws_emr_launch/control_plane/__init__.py
aws_emr_launch/control_plane/constructs/__init__.py
aws_emr_launch/control_plane/constructs/control_plane_stack.py
aws_emr_launch/control_plane/constructs/lambdas/__init__.py
aws_emr_launch/control_plane/constructs/lambdas/apis.py
aws_emr_launch/control_plane/lambda_sources/__init__.py
aws_emr_launch/control_plane/lambda_sources/apis/get_list_apis.py
aws_emr_launch/lambda_sources/LICENSE
aws_emr_launch/lambda_sources/__init__.py
aws_emr_launch/lambda_sources/emr_utilities/check_cluster_status/__init__.py
aws_emr_launch/lambda_sources/emr_utilities/check_cluster_status/lambda_source.py
aws_emr_launch/lambda_sources/emr_utilities/fail_if_cluster_running/__init__.py
aws_emr_launch/lambda_sources/emr_utilities/fail_if_cluster_running/lambda_source.py
aws_emr_launch-2.0.1.dist-info/LICENSE
aws_emr_launch-2.0.1.dist-info/METADATA
aws_emr_launch-2.0.1.dist-info/NOTICE
aws_emr_launch-2.0.1.dist-info/VERSION
aws_emr_launch-2.0.1.dist-info/WHEEL
aws_emr_launch-2.0.1.dist-info/top_level.txt
aws_emr_launch-2.0.1.dist-info/RECORD
