Metadata-Version: 2.1
Name: aws-emr-launch
Version: 2.0.1
Summary: AWS EMR Launch modules
Home-page: https://github.com/awslabs/aws-emr-launch/
Author: Chauncy McCaughey
Author-email: chamcca@amazon.com
License: UNKNOWN
Keywords: aws,cdk
Platform: UNKNOWN
Classifier: Development Status :: 5 - Production/Stable
Classifier: Intended Audience :: Developers
Classifier: License :: OSI Approved :: Apache Software License
Classifier: Programming Language :: JavaScript
Classifier: Programming Language :: Python :: 3 :: Only
Classifier: Programming Language :: Python :: 3.6
Classifier: Programming Language :: Python :: 3.7
Classifier: Programming Language :: Python :: 3.8
Classifier: Topic :: Software Development :: Code Generators
Classifier: Topic :: Utilities
Classifier: Typing :: Typed
Requires-Python: >=3.6
License-File: LICENSE
License-File: NOTICE
License-File: VERSION
Requires-Dist: logzero (~=1.5.0)
